[
  {"model":"core.achievement","pk":1,"fields":{"title":"Ən Yaxşı Baş Aşpaz","achievement_type":"gold_medal","issuer":"Azərbaycan Kulinariya Federasiyası","description":"Milli kulinariya yarışmasında ən yaxşı baş aşpaz nominasiyasında qızıl medal.","year":2018,"competition_name":"Azərbaycan Kulinariya Çempionatı","image":"","is_active":true,"order":1,"created_at":"2026-01-01T00:00:00Z","updated_at":"2026-01-01T00:00:00Z"}},
  {"model":"core.achievement","pk":2,"fields":{"title":"Ən Yaxşı Milli Yemək","achievement_type":"gold_medal","issuer":"Azərbaycan Kulinariya Federasiyası","description":"Ənənəvi Azərbaycan yeməklərinin hazırlanması üzrə qızıl medal.","year":2018,"competition_name":"Azərbaycan Kulinariya Çempionatı","image":"","is_active":true,"order":2,"created_at":"2026-01-01T00:00:00Z","updated_at":"2026-01-01T00:00:00Z"}},
  {"model":"core.achievement","pk":3,"fields":{"title":"İnnovasiya Menyusu","achievement_type":"gold_medal","issuer":"Beynəlxalq Aşpazlar Assosiasiyası","description":"Yeni menyu konsepsiyası yaradılması üzrə beynəlxalq qızıl medal.","year":2019,"competition_name":"Beynəlxalq Kulinariya Festivalı","image":"","is_active":true,"order":3,"created_at":"2026-01-01T00:00:00Z","updated_at":"2026-01-01T00:00:00Z"}},
  {"model":"core.achievement","pk":4,"fields":{"title":"Ən Yaxşı Qonaqpərvərlik","achievement_type":"gold_medal","issuer":"Azərbaycan Turizm Federasiyası","description":"Restoran qonaqpərvərliyi və servis keyfiyyəti üzrə qızıl medal.","year":2019,"competition_name":"Azərbaycan Turizm Mükafatları","image":"","is_active":true,"order":4,"created_at":"2026-01-01T00:00:00Z","updated_at":"2026-01-01T00:00:00Z"}},
  {"model":"core.achievement","pk":5,"fields":{"title":"Ən Yaxşı Deserт Aşpazı","achievement_type":"gold_medal","issuer":"Azərbaycan Kulinariya Federasiyası","description":"Desert hazırlanması üzrə milli çempionatda qızıl medal.","year":2019,"competition_name":"Milli Kulinariya Çempionatı","image":"","is_active":true,"order":5,"created_at":"2026-01-01T00:00:00Z","updated_at":"2026-01-01T00:00:00Z"}},
  {"model":"core.achievement","pk":6,"fields":{"title":"Restoran İdarəçiliyi Üzrə Üstünlük","achievement_type":"gold_medal","issuer":"Azərbaycan Sahibkarlıq Assosiasiyası","description":"Restoran idarəçiliyi sahəsindəki mükəmməl nəticələrə görə qızıl medal.","year":2020,"competition_name":"Azərbaycan İş Mükafatları","image":"","is_active":true,"order":6,"created_at":"2026-01-01T00:00:00Z","updated_at":"2026-01-01T00:00:00Z"}},
  {"model":"core.achievement","pk":7,"fields":{"title":"Sehirli Aşpaz — Qızıl Medal","achievement_type":"gold_medal","issuer":"İctimai TV","description":"Sehirli Aşpaz TV müsabiqəsində göstərilən mükəmməl nəticəyə görə mükafat.","year":2020,"competition_name":"Sehirli Aşpaz TV Müsabiqəsi","image":"","is_active":true,"order":7,"created_at":"2026-01-01T00:00:00Z","updated_at":"2026-01-01T00:00:00Z"}},
  {"model":"core.achievement","pk":8,"fields":{"title":"Ən Yaxşı Orta Şərq Mətbəxi","achievement_type":"gold_medal","issuer":"Beynəlxalq Kulinariya İnstitutu","description":"Orta Şərq kulinariya texnikası üzrə beynəlxalq yarışmada qızıl medal.","year":2020,"competition_name":"Beynəlxalq Kulinariya Olimpiadası","image":"","is_active":true,"order":8,"created_at":"2026-01-01T00:00:00Z","updated_at":"2026-01-01T00:00:00Z"}},
  {"model":"core.achievement","pk":9,"fields":{"title":"Ustad Müsabiqəsi — Finalist Mükafatı","achievement_type":"gold_medal","issuer":"Space TV","description":"Ustad kulinariya müsabiqəsinin finalında göstərilən gözəl nəticəyə görə qızıl medal.","year":2021,"competition_name":"Ustad TV Müsabiqəsi","image":"","is_active":true,"order":9,"created_at":"2026-01-01T00:00:00Z","updated_at":"2026-01-01T00:00:00Z"}},
  {"model":"core.achievement","pk":10,"fields":{"title":"Azərbaycan Mətbəxinin Təbliği","achievement_type":"gold_medal","issuer":"Azərbaycan Mədəniyyət Nazirliyi","description":"Azərbaycan milli mətbəxinin beynəlxalq səviyyədə tanıdılmasına verdiyi töhfəyə görə qızıl medal.","year":2021,"competition_name":"Milli Mədəniyyət Mükafatları","image":"","is_active":true,"order":10,"created_at":"2026-01-01T00:00:00Z","updated_at":"2026-01-01T00:00:00Z"}},
  {"model":"core.achievement","pk":11,"fields":{"title":"Ən Yaxşı Et Yeməkləri Aşpazı","achievement_type":"gold_medal","issuer":"Azərbaycan Kulinariya Federasiyası","description":"Et yeməklərinin hazırlanması üzrə milli yarışmada qızıl medal.","year":2021,"competition_name":"Milli Kulinariya Çempionatı","image":"","is_active":true,"order":11,"created_at":"2026-01-01T00:00:00Z","updated_at":"2026-01-01T00:00:00Z"}},
  {"model":"core.achievement","pk":12,"fields":{"title":"Rusiyada Qurme — Beynəlxalq Nümayəndə","achievement_type":"gold_medal","issuer":"Rusiya Federal TV","description":"Rusiyada Qurme verilişindəki mükəmməl iştirakı üçün xüsusi qızıl medal.","year":2021,"competition_name":"Rusiyada Qurme TV Verilişi","image":"","is_active":true,"order":12,"created_at":"2026-01-01T00:00:00Z","updated_at":"2026-01-01T00:00:00Z"}},
  {"model":"core.achievement","pk":13,"fields":{"title":"Ən Yaxşı Restoran Menyusu","achievement_type":"gold_medal","issuer":"Azərbaycan Restoran Assosiasiyası","description":"İlin ən yaxşı restoran menyusu yarışmasında qızıl medal.","year":2022,"competition_name":"Azərbaycan Restoran Mükafatları","image":"","is_active":true,"order":13,"created_at":"2026-01-01T00:00:00Z","updated_at":"2026-01-01T00:00:00Z"}},
  {"model":"core.achievement","pk":14,"fields":{"title":"Xörək Bəzəmə Ustası","achievement_type":"gold_medal","issuer":"Beynəlxalq Aşpazlar Birliyi","description":"Yemək bəzəmə (food decoration) üzrə beynəlxalq yarışmada qızıl medal.","year":2022,"competition_name":"Beynəlxalq Food Art Yarışması","image":"","is_active":true,"order":14,"created_at":"2026-01-01T00:00:00Z","updated_at":"2026-01-01T00:00:00Z"}},
  {"model":"core.achievement","pk":15,"fields":{"title":"Aclıq Oyunları — Ən Yaxşı Taktika","achievement_type":"gold_medal","issuer":"Xəzər TV","description":"Aclıq Oyunları müsabiqəsindəki strateci oyun taktikasına görə xüsusi qızıl medal.","year":2022,"competition_name":"Aclıq Oyunları TV Müsabiqəsi","image":"","is_active":true,"order":15,"created_at":"2026-01-01T00:00:00Z","updated_at":"2026-01-01T00:00:00Z"}},
  {"model":"core.achievement","pk":16,"fields":{"title":"Ən Yaxşı Balıq Yeməkləri","achievement_type":"gold_medal","issuer":"Azərbaycan Kulinariya Federasiyası","description":"Balıq yeməklərinin hazırlanması üzrə ixtisaslaşdırılmış yarışmada qızıl medal.","year":2022,"competition_name":"Xəzər Kulinariya Festivalı","image":"","is_active":true,"order":16,"created_at":"2026-01-01T00:00:00Z","updated_at":"2026-01-01T00:00:00Z"}},
  {"model":"core.achievement","pk":17,"fields":{"title":"İlin Restoranı — Masallı Hotel","achievement_type":"gold_medal","issuer":"Azərbaycan Turizm Nazirliyi","description":"Masallı Hotel Restoranının idarə olunmasındakı mükəmməllik üçün İlin Restoranı qızıl medalı.","year":2022,"competition_name":"Azərbaycan Turizm Mükafatları","image":"","is_active":true,"order":17,"created_at":"2026-01-01T00:00:00Z","updated_at":"2026-01-01T00:00:00Z"}},
  {"model":"core.achievement","pk":18,"fields":{"title":"Ən Yaxşı Şorba Aşpazı","achievement_type":"gold_medal","issuer":"Azərbaycan Kulinariya Federasiyası","description":"Milli şorba növlərinin hazırlanması üzrə yarışmada qızıl medal.","year":2023,"competition_name":"Milli Kulinariya Çempionatı","image":"","is_active":true,"order":18,"created_at":"2026-01-01T00:00:00Z","updated_at":"2026-01-01T00:00:00Z"}},
  {"model":"core.achievement","pk":19,"fields":{"title":"Organic Mətbəx İnnovasiyası","achievement_type":"gold_medal","issuer":"Azərbaycan Ekoloji Cəmiyyəti","description":"Kəndli Organic Fastfood konsepsiyasının yaradılmasına görə innovasiya qızıl medalı.","year":2023,"competition_name":"Azərbaycan Ekoloji Mükafatları","image":"","is_active":true,"order":19,"created_at":"2026-01-01T00:00:00Z","updated_at":"2026-01-01T00:00:00Z"}},
  {"model":"core.achievement","pk":20,"fields":{"title":"Ən Yaxşı Saç Aşpazı","achievement_type":"gold_medal","issuer":"Azərbaycan Kulinariya Federasiyası","description":"Azərbaycanın milli yeməyi plov hazırlanması üzrə yarışmada qızıl medal.","year":2023,"competition_name":"Milli Plov Çempionatı","image":"","is_active":true,"order":20,"created_at":"2026-01-01T00:00:00Z","updated_at":"2026-01-01T00:00:00Z"}},
  {"model":"core.achievement","pk":21,"fields":{"title":"Restoran Xidməti Üzrə Üstünlük","achievement_type":"gold_medal","issuer":"Azərbaycan Xidmət Keyfiyyəti Agentliyi","description":"Müştəri xidməti və qonaqpərvərlik standartları üzrə mükəmməl nəticəyə görə qızıl medal.","year":2023,"competition_name":"Azərbaycan Xidmət Mükafatları","image":"","is_active":true,"order":21,"created_at":"2026-01-01T00:00:00Z","updated_at":"2026-01-01T00:00:00Z"}},
  {"model":"core.achievement","pk":22,"fields":{"title":"Dadlı Dünya — Ən Yaxşı İştirakçı","achievement_type":"gold_medal","issuer":"AzTV","description":"Dadlı Dünya verilişindəki parlaq iştirakı üçün xüsusi qızıl medal.","year":2023,"competition_name":"Dadlı Dünya TV Verilişi","image":"","is_active":true,"order":22,"created_at":"2026-01-01T00:00:00Z","updated_at":"2026-01-01T00:00:00Z"}},
  {"model":"core.achievement","pk":23,"fields":{"title":"Ən Yaxşı Cənub Azərbaycan Mətbəxi","achievement_type":"gold_medal","issuer":"Lənkəran-Astara Bölgə İdarəsi","description":"Cənub bölgəsinin kulinariya ənənələrinin qorunması və inkişafına verdiyi töhfəyə görə qızıl medal.","year":2024,"competition_name":"Cənub Kulinariya Festivalı","image":"","is_active":true,"order":23,"created_at":"2026-01-01T00:00:00Z","updated_at":"2026-01-01T00:00:00Z"}},
  {"model":"core.achievement","pk":24,"fields":{"title":"Pub Lounge Konsepsiyası Üzrə Üstünlük","achievement_type":"gold_medal","issuer":"Azərbaycan Ehtiyat Sənayesi Assosiasiyası","description":"Terras Masallı Pub Lounge-un unikal konsepsiyası üçün qızıl medal.","year":2024,"competition_name":"Azərbaycan Qonaqpərvərlik Mükafatları","image":"","is_active":true,"order":24,"created_at":"2026-01-01T00:00:00Z","updated_at":"2026-01-01T00:00:00Z"}},
  {"model":"core.achievement","pk":25,"fields":{"title":"Ən Yaxşı Tərəvəz Yeməkləri","achievement_type":"gold_medal","issuer":"Azərbaycan Kulinariya Federasiyası","description":"Tərəvəz əsaslı yeməklərin hazırlanması üzrə yarışmada qızıl medal.","year":2024,"competition_name":"Milli Kulinariya Çempionatı","image":"","is_active":true,"order":25,"created_at":"2026-01-01T00:00:00Z","updated_at":"2026-01-01T00:00:00Z"}},
  {"model":"core.achievement","pk":26,"fields":{"title":"Azərbaycan Kulinariya Səfiri","achievement_type":"gold_medal","issuer":"Azərbaycan Xarici İşlər Nazirliyi","description":"Azərbaycan mətbəxini beynəlxalq səviyyədə təmsil etməsinə görə xüsusi qızıl medal.","year":2024,"competition_name":"Beynəlxalq Kulinariya Diplomatiyası","image":"","is_active":true,"order":26,"created_at":"2026-01-01T00:00:00Z","updated_at":"2026-01-01T00:00:00Z"}},
  {"model":"core.achievement","pk":27,"fields":{"title":"mestixumarcay — Ən Yaxşı Yeni Brend","achievement_type":"gold_medal","issuer":"Azərbaycan Sahibkarlıq İnkişafı Fondu","description":"mestixumarcay çay brendinin yaradılması üzrə innovasiya və sahibkarlıq qızıl medalı.","year":2025,"competition_name":"Azərbaycan Startap Mükafatları","image":"","is_active":true,"order":27,"created_at":"2026-01-01T00:00:00Z","updated_at":"2026-01-01T00:00:00Z"}},
  {"model":"core.achievement","pk":28,"fields":{"title":"Masallı Regionunun Ən Yaxşı Restoratoru","achievement_type":"gold_medal","issuer":"Masallı Rayon İcra Hakimiyyəti","description":"Masallı rayonunun qastronomi inkişafına verdiyi böyük töhfəyə görə verilən xüsusi qızıl medal.","year":2025,"competition_name":"Masallı Region Mükafatları","image":"","is_active":true,"order":28,"created_at":"2026-01-01T00:00:00Z","updated_at":"2026-01-01T00:00:00Z"}}
]
